{
  "ts": "2026-04-08T06:55:10.509Z",
  "items": [
    {
      "code": "^GSPC",
      "name": "S&P 500",
      "ts": "2026-04-08T06:55:10.509Z",
      "price": 6616.85,
      "currency": "USD",
      "source": "stooq",
      "is_delayed": true
    },
    {
      "code": "^IXIC",
      "name": "Nasdaq",
      "ts": "2026-04-08T06:55:10.509Z",
      "price": 22017.85,
      "currency": "USD",
      "source": "stooq",
      "is_delayed": true
    },
    {
      "code": "^DJI",
      "name": "Dow Jones",
      "ts": "2026-04-08T06:55:10.509Z",
      "price": 46584.46,
      "currency": "USD",
      "source": "stooq",
      "is_delayed": true
    }
  ]
}