{
  "ts": "2026-04-01T23:58:09.191Z",
  "items": [
    {
      "code": "^GSPC",
      "name": "S&P 500",
      "ts": "2026-04-01T23:58:09.191Z",
      "price": 6575.32,
      "currency": "USD",
      "source": "stooq",
      "is_delayed": true
    },
    {
      "code": "^IXIC",
      "name": "Nasdaq",
      "ts": "2026-04-01T23:58:09.191Z",
      "price": 21840.95,
      "currency": "USD",
      "source": "stooq",
      "is_delayed": true
    },
    {
      "code": "^DJI",
      "name": "Dow Jones",
      "ts": "2026-04-01T23:58:09.191Z",
      "price": 46565.74,
      "currency": "USD",
      "source": "stooq",
      "is_delayed": true
    }
  ]
}