{
  "ts": "2026-04-14T20:39:09.700Z",
  "items": [
    {
      "code": "^GSPC",
      "name": "S&P 500",
      "ts": "2026-04-14T20:39:09.700Z",
      "price": 6967.4,
      "currency": "USD",
      "source": "stooq",
      "is_delayed": true
    },
    {
      "code": "^IXIC",
      "name": "Nasdaq",
      "ts": "2026-04-14T20:39:09.700Z",
      "price": 23639.084,
      "currency": "USD",
      "source": "stooq",
      "is_delayed": true
    },
    {
      "code": "^DJI",
      "name": "Dow Jones",
      "ts": "2026-04-14T20:39:09.700Z",
      "price": 48536,
      "currency": "USD",
      "source": "stooq",
      "is_delayed": true
    }
  ]
}