{
  "ts": "2026-04-13T14:08:58.319Z",
  "items": [
    {
      "code": "^GSPC",
      "name": "S&P 500",
      "ts": "2026-04-13T14:08:58.319Z",
      "price": 6817.2,
      "currency": "USD",
      "source": "stooq",
      "is_delayed": true
    },
    {
      "code": "^IXIC",
      "name": "Nasdaq",
      "ts": "2026-04-13T14:08:58.319Z",
      "price": 22950.121,
      "currency": "USD",
      "source": "stooq",
      "is_delayed": true
    },
    {
      "code": "^DJI",
      "name": "Dow Jones",
      "ts": "2026-04-13T14:08:58.319Z",
      "price": 47682.2,
      "currency": "USD",
      "source": "stooq",
      "is_delayed": true
    }
  ]
}